odoo/addons/stock_valuation_layer_accounting_date/README.rst
odoo/addons/stock_valuation_layer_accounting_date/__init__.py
odoo/addons/stock_valuation_layer_accounting_date/__manifest__.py
odoo/addons/stock_valuation_layer_accounting_date/hooks.py
odoo/addons/stock_valuation_layer_accounting_date/i18n/it.po
odoo/addons/stock_valuation_layer_accounting_date/i18n/ja.po
odoo/addons/stock_valuation_layer_accounting_date/i18n/stock_valuation_layer_accounting_date.pot
odoo/addons/stock_valuation_layer_accounting_date/models/__init__.py
odoo/addons/stock_valuation_layer_accounting_date/models/stock_valuation_layer.py
odoo/addons/stock_valuation_layer_accounting_date/readme/CONTRIBUTORS.rst
odoo/addons/stock_valuation_layer_accounting_date/readme/DESCRIPTION.rst
odoo/addons/stock_valuation_layer_accounting_date/readme/USAGE.rst
odoo/addons/stock_valuation_layer_accounting_date/static/description/icon.png
odoo/addons/stock_valuation_layer_accounting_date/static/description/index.html
odoo/addons/stock_valuation_layer_accounting_date/tests/__init__.py
odoo/addons/stock_valuation_layer_accounting_date/tests/test_stock_valuation_layer_accounting_date.py
odoo/addons/stock_valuation_layer_accounting_date/views/stock_valuation_layer_views.xml
odoo/addons/stock_valuation_layer_accounting_date/wizard/__init__.py
odoo/addons/stock_valuation_layer_accounting_date/wizard/stock_quantity_history.py
odoo/addons/stock_valuation_layer_accounting_date/wizard/stock_quantity_history.xml
odoo_addon_stock_valuation_layer_accounting_date-16.0.1.0.2.dist-info/METADATA
odoo_addon_stock_valuation_layer_accounting_date-16.0.1.0.2.dist-info/WHEEL
odoo_addon_stock_valuation_layer_accounting_date-16.0.1.0.2.dist-info/top_level.txt
odoo_addon_stock_valuation_layer_accounting_date-16.0.1.0.2.dist-info/RECORD
